nx_itertools/__init__.py
nx_itertools/extra.py
nx_itertools/recipes.py
nx_itertools/version.txt
nx_itertools-1.3.0.dist-info/DESCRIPTION.rst
nx_itertools-1.3.0.dist-info/METADATA
nx_itertools-1.3.0.dist-info/RECORD
nx_itertools-1.3.0.dist-info/WHEEL
nx_itertools-1.3.0.dist-info/metadata.json
nx_itertools-1.3.0.dist-info/top_level.txt
tests/__init__.py
tests/test_all_equal.py
tests/test_chunk.py
tests/test_consume.py
tests/test_divide.py
tests/test_divide_sizes.py
tests/test_dotproduct.py
tests/test_first_true.py
tests/test_flatten.py
tests/test_grouper.py
tests/test_iter_except.py
tests/test_multi_map.py
tests/test_ncycles.py
tests/test_nth.py
tests/test_padnone.py
tests/test_pairwise_extra.py
tests/test_pairwise_recipes.py
tests/test_partition_extra.py
tests/test_partition_recipes.py
tests/test_powerset_extra.py
tests/test_powerset_recipes.py
tests/test_quantify.py
tests/test_random_combination.py
tests/test_random_combination_with_replacement.py
tests/test_random_permutation.py
tests/test_random_product.py
tests/test_repeatfunc.py
tests/test_roundrobin.py
tests/test_split.py
tests/test_tabulate.py
tests/test_tail.py
tests/test_take.py
tests/test_unique_everseen.py
tests/test_unique_justseen.py
