Metadata-Version: 2.0
Name: nx-itertools
Version: 1.3.0
Summary: Itertools shim with recipes and extras
Home-page: https://github.com/nxdevel/nx_itertools
Author: A Bradford
Author-email: nxdevel@users.noreply.github.com
License: MIT
Keywords: development utilities itertools recipes
Platform: UNKNOWN
Classifier: Development Status :: 5 - Production/Stable
Classifier: License :: OSI Approved :: MIT License
Classifier: Programming Language :: Python :: 3 :: Only
Classifier: Topic :: Software Development :: Libraries
Classifier: Topic :: Utilities
Classifier: Intended Audience :: Developers
